odoo/addons/account_vat_period_end_statement/README.rst
odoo/addons/account_vat_period_end_statement/__init__.py
odoo/addons/account_vat_period_end_statement/__manifest__.py
odoo/addons/account_vat_period_end_statement/i18n/account_vat_period_end_statement.pot
odoo/addons/account_vat_period_end_statement/i18n/am.po
odoo/addons/account_vat_period_end_statement/i18n/ar.po
odoo/addons/account_vat_period_end_statement/i18n/bg.po
odoo/addons/account_vat_period_end_statement/i18n/bs.po
odoo/addons/account_vat_period_end_statement/i18n/ca.po
odoo/addons/account_vat_period_end_statement/i18n/ca_ES.po
odoo/addons/account_vat_period_end_statement/i18n/cs.po
odoo/addons/account_vat_period_end_statement/i18n/da.po
odoo/addons/account_vat_period_end_statement/i18n/de.po
odoo/addons/account_vat_period_end_statement/i18n/el_GR.po
odoo/addons/account_vat_period_end_statement/i18n/en_AU.po
odoo/addons/account_vat_period_end_statement/i18n/en_GB.po
odoo/addons/account_vat_period_end_statement/i18n/es.po
odoo/addons/account_vat_period_end_statement/i18n/es_AR.po
odoo/addons/account_vat_period_end_statement/i18n/es_CL.po
odoo/addons/account_vat_period_end_statement/i18n/es_CO.po
odoo/addons/account_vat_period_end_statement/i18n/es_CR.po
odoo/addons/account_vat_period_end_statement/i18n/es_DO.po
odoo/addons/account_vat_period_end_statement/i18n/es_EC.po
odoo/addons/account_vat_period_end_statement/i18n/es_ES.po
odoo/addons/account_vat_period_end_statement/i18n/es_MX.po
odoo/addons/account_vat_period_end_statement/i18n/es_PE.po
odoo/addons/account_vat_period_end_statement/i18n/es_PY.po
odoo/addons/account_vat_period_end_statement/i18n/es_VE.po
odoo/addons/account_vat_period_end_statement/i18n/et.po
odoo/addons/account_vat_period_end_statement/i18n/eu.po
odoo/addons/account_vat_period_end_statement/i18n/fa.po
odoo/addons/account_vat_period_end_statement/i18n/fi.po
odoo/addons/account_vat_period_end_statement/i18n/fr.po
odoo/addons/account_vat_period_end_statement/i18n/fr_CA.po
odoo11_addon_account_vat_period_end_statement-11.0.1.0.0.99.dev9.dist-info/METADATA
odoo11_addon_account_vat_period_end_statement-11.0.1.0.0.99.dev9.dist-info/WHEEL
odoo11_addon_account_vat_period_end_statement-11.0.1.0.0.99.dev9.dist-info/top_level.txt
odoo11_addon_account_vat_period_end_statement-11.0.1.0.0.99.dev9.dist-info/RECORD
