Metadata-Version: 2.1
Name: odoo11-addon-account_vat_period_end_statement
Version: 11.0.1.0.0.99.dev9
Summary: Liquidazione IVA
Home-page: https://github.com/OCA/l10n-italy/tree/11.0/account_vat_period_end_statement
Author: Agile Business Group, Odoo Community Association (OCA), LinkIt Spa
Author-email: support@odoo-community.org
License: AGPL-3
Classifier: Programming Language :: Python
Classifier: Framework :: Odoo
Classifier: Framework :: Odoo :: 11.0
Classifier: License :: OSI Approved :: GNU Affero General Public License v3
Requires-Python: >=2.7, !=3.0.*, !=3.1.*, !=3.2.*, !=3.3.*, !=3.4.*
Requires-Dist: odoo11-addon-account-tax-balance
Requires-Dist: odoo11-addon-date-range
Requires-Dist: odoo11-addon-l10n-it-account
Requires-Dist: odoo11-addon-l10n-it-fiscalcode
Requires-Dist: odoo<11.1dev,>=11.0a
